sharokey/__init__.py
sharokey/client.py
sharokey/crypto.py
sharokey/exceptions.py
sharokey/models.py
sharokey-1.0.0.dist-info/LICENSE
sharokey-1.0.0.dist-info/METADATA
sharokey-1.0.0.dist-info/WHEEL
sharokey-1.0.0.dist-info/top_level.txt
sharokey-1.0.0.dist-info/RECORD
