Metadata-Version: 2.1
Name: sharokey
Version: 1.0.0
Summary: Sharokey Python SDK for secure secret sharing with Zero Knowledge encryption
Home-page: https://github.com/sharokey/python-sdk
Author: Sharokey Team
Author-email: support@sharokey.com
Project-URL: Bug Reports, https://github.com/sharokey/python-sdk/issues
Project-URL: Documentation, https://docs.sharokey.com/python
Project-URL: Source, https://github.com/sharokey/python-sdk
Keywords: secrets,encryption,security,zero-knowledge,api,sharokey
Classifier: Development Status :: 5 - Production/Stable
Classifier: Intended Audience :: Developers
Classifier: License :: OSI Approved :: MIT License
Classifier: Operating System :: OS Independent
Classifier: Programming Language :: Python :: 3
Classifier: Programming Language :: Python :: 3.7
Classifier: Programming Language :: Python :: 3.8
Classifier: Programming Language :: Python :: 3.9
Classifier: Programming Language :: Python :: 3.10
Classifier: Programming Language :: Python :: 3.11
Classifier: Topic :: Security :: Cryptography
Classifier: Topic :: Software Development :: Libraries :: Python Modules
Requires-Python: >=3.7
License-File: LICENSE
Requires-Dist: aiohttp<4.0.0,>=3.8.0
Requires-Dist: aiofiles<25.0.0,>=23.0.0
Requires-Dist: cryptography<43.0.0,>=41.0.0
Provides-Extra: dev
Requires-Dist: pytest<9.0.0,>=7.0.0; extra == "dev"
Requires-Dist: pytest-asyncio<1.0.0,>=0.21.0; extra == "dev"
Requires-Dist: pytest-cov<6.0.0,>=4.0.0; extra == "dev"
Requires-Dist: black<25.0.0,>=23.0.0; extra == "dev"
Requires-Dist: isort<6.0.0,>=5.12.0; extra == "dev"
Requires-Dist: mypy<2.0.0,>=1.5.0; extra == "dev"
Requires-Dist: flake8<8.0.0,>=6.0.0; extra == "dev"
